mojap_metadata/__init__.py
mojap_metadata/converters/__init__.py
mojap_metadata/converters/arrow_converter/__init__.py
mojap_metadata/converters/aws_iceberg_converter/__init__.py
mojap_metadata/converters/aws_iceberg_converter/exceptions.py
mojap_metadata/converters/aws_iceberg_converter/iceberg_metadata.py
mojap_metadata/converters/aws_iceberg_converter/specs/__init__.py
mojap_metadata/converters/aws_iceberg_converter/specs/alter_add_columns.sql
mojap_metadata/converters/aws_iceberg_converter/specs/alter_change_column.sql
mojap_metadata/converters/aws_iceberg_converter/specs/alter_drop_column.sql
mojap_metadata/converters/aws_iceberg_converter/specs/create.sql
mojap_metadata/converters/etl_manager_converter/__init__.py
mojap_metadata/converters/glue_converter/README.md
mojap_metadata/converters/glue_converter/__init__.py
mojap_metadata/converters/glue_converter/specs/__init__.py
mojap_metadata/converters/glue_converter/specs/hive_json_spec.json
mojap_metadata/converters/glue_converter/specs/lazy_csv_spec.json
mojap_metadata/converters/glue_converter/specs/open_csv_spec.json
mojap_metadata/converters/glue_converter/specs/openx_json_spec.json
mojap_metadata/converters/glue_converter/specs/parquet_spec.json
mojap_metadata/converters/postgres_converter/README.md
mojap_metadata/converters/postgres_converter/__init__.py
mojap_metadata/converters/postgres_converter/connect.py
mojap_metadata/converters/postgres_converter/postgres_functions.py
mojap_metadata/converters/sqlalchemy_converter/README.md
mojap_metadata/converters/sqlalchemy_converter/__init__.py
mojap_metadata/converters/sqlalchemy_converter/utils.py
mojap_metadata/metadata/__init__.py
mojap_metadata/metadata/metadata.py
mojap_metadata/metadata/specs/__init__.py
mojap_metadata/metadata/specs/table_schema.json
mojap_metadata-1.16.0.dist-info/LICENSE
mojap_metadata-1.16.0.dist-info/METADATA
mojap_metadata-1.16.0.dist-info/WHEEL
mojap_metadata-1.16.0.dist-info/RECORD
