Metadata-Version: 2.3
Name: mojap-metadata
Version: 1.16.0
Summary: A python package to manage metadata
License: MIT
Author: MoJ Data Engineering
Author-email: dataengineering@digital.justice.gov.uk
Requires-Python: >=3.9,<4
Classifier: License :: OSI Approved :: MIT License
Classifier: Programming Language :: Python :: 3
Classifier: Programming Language :: Python :: 3.9
Classifier: Programming Language :: Python :: 3.10
Classifier: Programming Language :: Python :: 3.11
Classifier: Programming Language :: Python :: 3.12
Classifier: Programming Language :: Python :: 3.13
Provides-Extra: arrow
Provides-Extra: aws-iceberg
Provides-Extra: etl-manager
Provides-Extra: postgres
Requires-Dist: Jinja2 (>=2.10.1)
Requires-Dist: PyYAML (>=6.0,<7.0)
Requires-Dist: SQLAlchemy[postgres] (>=1.4.27,<2.0.0) ; extra == "postgres"
Requires-Dist: awswrangler[aws-iceberg] (>=3.10.0) ; extra == "aws-iceberg"
Requires-Dist: dataengineeringutils3 (>=1.4.0)
Requires-Dist: etl-manager (>=7.4,<8.0) ; extra == "etl-manager"
Requires-Dist: jsonschema (>=3.0.0)
Requires-Dist: parameterized (==0.7.*)
Requires-Dist: psycopg2[postgres] (>=2.9.2,<3.0.0) ; extra == "postgres"
Requires-Dist: pyarrow (>=14.0.0) ; extra == "arrow"
Requires-Dist: testing.postgresql[postgres] (>=1.3.0,<2.0.0) ; extra == "postgres"
